README.md
setup.py
PowerI2C/__init__.py
PowerI2C/power.py
PowerI2C.egg-info/PKG-INFO
PowerI2C.egg-info/SOURCES.txt
PowerI2C.egg-info/dependency_links.txt
PowerI2C.egg-info/top_level.txt