Metadata-Version: 2.1
Name: PowerI2C
Version: 0.1.7
Summary: Esta libreria se conecta a un arduino mediante protocolo I2C, donde se pueden ingresar comandos para solicitar datos tipo float al arduino
Author: Cristian Martinez y Alberto Mercado
